[{"business_status": "OPERATIONAL", "geometry": {"location": {"lat": 51.0508373, "lng": 13.7365918}, "viewport": {"northeast": {"lat": 51.05207247989271, "lng": 13.73786152989272}, "southwest": {"lat": 51.04937282010727, "lng": 13.73516187010728}}}, "icon": "https://maps.gstatic.com/mapfiles/place_api/icons/v1/png_71/bar-71.png", "icon_background_color": "#FF9E67", "icon_mask_base_uri": "https://maps.gstatic.com/mapfiles/place_api/icons/v2/bar_pinlet", "name": "Shamrock Irish Bar & Restaurant", "opening_hours": {"open_now": true}, "photos": [{"height": 3024, "html_attributions": ["<a href=\"https://maps.google.com/maps/contrib/118189383708413177587\">Philipp Seidel</a>"], "photo_reference": "AUGGfZmLhwGVpf7pRYf3oHoeiJCPdkgOEMxQIBa5LHi-AKqcD3GfyY--45fJvcGS2zVhwkWngOanUJteDvk5zOWmHDxXdKJoRGLEP8eyCqXt_yLBpn19DWYGJqHo2IRf6JSBBjbE8W2MGXrkgA4Qx01wUeEDmTxa1MHhXxNDMVGfE-IPNizT", "width": 4032}], "place_id": "ChIJe5JWNGbPCUcRgsN2caFryiQ", "plus_code": {"compound_code": "3P2P+8J Dresden, Germany", "global_code": "9F3M3P2P+8J"}, "price_level": 2, "rating": 4.4, "reference": "ChIJe5JWNGbPCUcRgsN2caFryiQ", "scope": "GOOGLE", "types": ["bar", "restaurant", "food", "point_of_interest", "establishment"], "user_ratings_total": 4730, "vicinity": "Wilsdruffer Str. 20, Dresden"}, {"business_status": "OPERATIONAL", "geometry": {"location": {"lat": 51.0677699, "lng": 13.7526256}, "viewport": {"northeast": {"lat": 51.06913842989272, "lng": 13.75392812989272}, "southwest": {"lat": 51.06643877010728, "lng": 13.75122847010728}}}, "icon": "https://maps.gstatic.com/mapfiles/place_api/icons/v1/png_71/bar-71.png", "icon_background_color": "#FF9E67", "icon_mask_base_uri": "https://maps.gstatic.com/mapfiles/place_api/icons/v2/bar_pinlet", "name": "Irish Fiddler - Dresden", "opening_hours": {"open_now": true}, "photos": [{"height": 3097, "html_attributions": ["<a href=\"https://maps.google.com/maps/contrib/108602034323649745118\">Frank Drechsel</a>"], "photo_reference": "AUGGfZlP9NI9j9SjqSo6zebIEUXXHgSnLVLugMvKV8UU6XGjA3sCq1tJfSwGvl9Fwzuu9XBnUvCK_DYe5n4RckoSiaOW0fSZFD3gbJ3Ju2w-2YRt3sLUUNhhDKw37RlRrz_tCqlJ4-O_QpKf14MlD2rDMSz9wZC-VntpGb7SGrnFIMbFgA-O", "width": 5506}], "place_id": "ChIJE937UznPCUcRdy9DcG7utYI", "plus_code": {"compound_code": "3Q93+43 Dresden, Germany", "global_code": "9F3M3Q93+43"}, "price_level": 2, "rating": 4.5, "reference": "ChIJE937UznPCUcRdy9DcG7utYI", "scope": "GOOGLE", "types": ["bar", "restaurant", "food", "point_of_interest", "establishment"], "user_ratings_total": 892, "vicinity": "Alaunstra\u00dfe 62, Dresden"}, {"business_status": "OPERATIONAL", "geometry": {"location": {"lat": 51.0701981, "lng": 13.7540951}, "viewport": {"northeast": {"lat": 51.07161342989273, "lng": 13.75539982989272}, "southwest": {"lat": 51.06891377010729, "lng": 13.75270017010728}}}, "icon": "https://maps.gstatic.com/mapfiles/place_api/icons/v1/png_71/bar-71.png", "icon_background_color": "#FF9E67", "icon_mask_base_uri": "https://maps.gstatic.com/mapfiles/place_api/icons/v2/bar_pinlet", "name": "T\u00edr na n\u00d3g", "opening_hours": {"open_now": true}, "photos": [{"height": 3024, "html_attributions": ["<a href=\"https://maps.google.com/maps/contrib/108845380096939017279\">Christian Fischer</a>"], "photo_reference": "AUGGfZnOw-726PEaYPemUz8ifUBaJeEqCXNK-OTO54UDjLScuMPLOrsyR9kEKCol0C-m5TEWNCwWoh9muSo0_AM89BCC2ZvK-21X4-YaQFlZs7R-agaBV8mNESp5D_qaLPRT9MWGr7Lw873sGQwDzdd4VBu5iIbXL84YkMxdJD3HxaCW9sCv", "width": 4032}], "place_id": "ChIJKSDH5zzPCUcRat_AH8IXp3M", "plus_code": {"compound_code": "3QC3+3J Dresden, Germany", "global_code": "9F3M3QC3+3J"}, "price_level": 2, "rating": 4.4, "reference": "ChIJKSDH5zzPCUcRat_AH8IXp3M", "scope": "GOOGLE", "types": ["bar", "restaurant", "food", "point_of_interest", "establishment"], "user_ratings_total": 350, "vicinity": "Bischofsweg 34, Dresden"}, {"business_status": "OPERATIONAL", "geometry": {"location": {"lat": 51.062518, "lng": 13.7518122}, "viewport": {"northeast": {"lat": 51.06387037989271, "lng": 13.75318202989272}, "southwest": {"lat": 51.06117072010727, "lng": 13.75048237010728}}}, "icon": "https://maps.gstatic.com/mapfiles/place_api/icons/v1/png_71/bar-71.png", "icon_background_color": "#FF9E67", "icon_mask_base_uri": "https://maps.gstatic.com/mapfiles/place_api/icons/v2/bar_pinlet", "name": "Bautzner Tor", "opening_hours": {"open_now": true}, "photos": [{"height": 4512, "html_attributions": ["<a href=\"https://maps.google.com/maps/contrib/113215562332284951560\">Swagato Sarkar</a>"], "photo_reference": "AUGGfZkVA2JurGVC9-nLPu2a4tz0L1ycp59gcM3NaFJKbUkt9SEQmMGuPLkhXks7HuyK0JTylLYVmmn0GBki5xno5tT4rpAqftkC-fCi2Mt2gWIUtQYNRdvhFQWNcoAU_reobZGHzpmawGG8DBy7696hml2ahsu-AmA6hciMK16LmK_qWaLN", "width": 6016}], "place_id": "ChIJaZosQT_PCUcResJLVg1iYAg", "plus_code": {"compound_code": "3Q62+XM Dresden, Germany", "global_code": "9F3M3Q62+XM"}, "price_level": 1, "rating": 4.6, "reference": "ChIJaZosQT_PCUcResJLVg1iYAg", "scope": "GOOGLE", "types": ["bar", "restaurant", "food", "point_of_interest", "establishment"], "user_ratings_total": 1218, "vicinity": "Hoyerswerdaer Str. 37, Dresden"}, {"business_status": "OPERATIONAL", "geometry": {"location": {"lat": 51.0334223, "lng": 13.7250358}, "viewport": {"northeast": {"lat": 51.03480252989272, "lng": 13.72634097989272}, "southwest": {"lat": 51.03210287010728, "lng": 13.72364132010728}}}, "icon": "https://maps.gstatic.com/mapfiles/place_api/icons/v1/png_71/bar-71.png", "icon_background_color": "#FF9E67", "icon_mask_base_uri": "https://maps.gstatic.com/mapfiles/place_api/icons/v2/bar_pinlet", "name": "Campus Bar & Restaurant Dresden", "opening_hours": {"open_now": true}, "photos": [{"height": 3024, "html_attributions": ["<a href=\"https://maps.google.com/maps/contrib/109448260157910281995\">Luckas Bach</a>"], "photo_reference": "AUGGfZm0eUXoOWJWsPTgremRVHi-IQpyq1McA2LxPlPvcrdh7JZgdiz0MXRW7yYYkxmBCFxfqGA2Elz7TNWrQOjpcgfWHjQjgbnAIVNn0POJMTbW_y8UA1GK7u2oKbVEA2oMGfrUKCUe6MmrInYqoPBdcbcb3GEfOCCZM2C_X0MPg6kuQG-1", "width": 4032}], "place_id": "ChIJraOAwMXFCUcR5toV8GYc8lg", "plus_code": {"compound_code": "2PMG+92 Dresden, Germany", "global_code": "9F3M2PMG+92"}, "rating": 4.3, "reference": "ChIJraOAwMXFCUcR5toV8GYc8lg", "scope": "GOOGLE", "types": ["bar", "restaurant", "food", "point_of_interest", "establishment"], "user_ratings_total": 602, "vicinity": "H\u00fcbnerstra\u00dfe 13, Dresden"}, {"business_status": "OPERATIONAL", "geometry": {"location": {"lat": 51.0689138, "lng": 13.7557375}, "viewport": {"northeast": {"lat": 51.07028267989272, "lng": 13.75701072989272}, "southwest": {"lat": 51.06758302010728, "lng": 13.75431107010727}}}, "icon": "https://maps.gstatic.com/mapfiles/place_api/icons/v1/png_71/restaurant-71.png", "icon_background_color": "#FF9E67", "icon_mask_base_uri": "https://maps.gstatic.com/mapfiles/place_api/icons/v2/restaurant_pinlet", "name": "Zapfanstalt", "opening_hours": {"open_now": true}, "photos": [{"height": 2268, "html_attributions": ["<a href=\"https://maps.google.com/maps/contrib/116610745433597648345\">Sebastian Faupel</a>"], "photo_reference": "AUGGfZmIom1pOzJLSKJelKkf7pebIdXswn4UTjqiqTIjnz8r_Y6_3NJNIQ8-PkrHPhjMJoYSvsFVh_5ALWUzshPFKdLMgCiMkQpK8LZhW2xKi0EccPuLMtqzcAZgZWVUXXZm2ODu1V5Tcp-BTrxLVwKPtD1-rJNUUArTG1-HBTXL9BPWmM12", "width": 4032}], "place_id": "ChIJfd5-fTzPCUcReDjt0PKjhN0", "plus_code": {"compound_code": "3Q94+H7 Dresden, Germany", "global_code": "9F3M3Q94+H7"}, "price_level": 2, "rating": 4.4, "reference": "ChIJfd5-fTzPCUcReDjt0PKjhN0", "scope": "GOOGLE", "types": ["restaurant", "bar", "food", "point_of_interest", "establishment"], "user_ratings_total": 914, "vicinity": "Sebnitzer Str. 15, Dresden"}, {"business_status": "OPERATIONAL", "geometry": {"location": {"lat": 51.053031, "lng": 13.7244047}, "viewport": {"northeast": {"lat": 51.05439772989272, "lng": 13.72571657989272}, "southwest": {"lat": 51.05169807010728, "lng": 13.72301692010728}}}, "icon": "https://maps.gstatic.com/mapfiles/place_api/icons/v1/png_71/bar-71.png", "icon_background_color": "#FF9E67", "icon_mask_base_uri": "https://maps.gstatic.com/mapfiles/place_api/icons/v2/bar_pinlet", "name": "Volt Bar", "opening_hours": {"open_now": true}, "photos": [{"height": 4032, "html_attributions": ["<a href=\"https://maps.google.com/maps/contrib/107126706428147225143\">Feriendomizil Barthoff</a>"], "photo_reference": "AUGGfZkAuCiq4q1Ut9vX8n-9wyx7vSHz4Z5EFQtC6EjtyYWqXdKuG1GNc3OdlR9Li5SmEfe-McC2o0v4vQqd--zVRgpk7rytK05SLgAgpOprown8HlBSqiW19-nF3GPpjYNZSomcQ3rRlWosfd1aacwNghmgqOcAYUnN7GIkhJTcUuqA_BgJ", "width": 3024}], "place_id": "ChIJXXpeVhbPCUcRrDhYOnAb1qc", "plus_code": {"compound_code": "3P3F+6Q Dresden, Germany", "global_code": "9F3M3P3F+6Q"}, "rating": 5, "reference": "ChIJXXpeVhbPCUcRrDhYOnAb1qc", "scope": "GOOGLE", "types": ["bar", "restaurant", "food", "point_of_interest", "establishment"], "user_ratings_total": 8, "vicinity": "Wettiner Pl. 1, Dresden"}, {"business_status": "OPERATIONAL", "geometry": {"location": {"lat": 51.0671455, "lng": 13.7541441}, "viewport": {"northeast": {"lat": 51.06845662989272, "lng": 13.75557262989272}, "southwest": {"lat": 51.06575697010728, "lng": 13.75287297010728}}}, "icon": "https://maps.gstatic.com/mapfiles/place_api/icons/v1/png_71/bar-71.png", "icon_background_color": "#FF9E67", "icon_mask_base_uri": "https://maps.gstatic.com/mapfiles/place_api/icons/v2/bar_pinlet", "name": "BARNEBY - Die Spielebar", "opening_hours": {"open_now": true}, "photos": [{"height": 667, "html_attributions": ["<a href=\"https://maps.google.com/maps/contrib/103397707433543235997\">A Google User</a>"], "photo_reference": "AUGGfZnAVAGo_Wn_ESbBXqVAkCliUvGZ1c6Do6ZjN06q_H2R5gBF1FdoNl_trpy2yIblFBOMjWV-fFk3KnZLzN-qvaSO7f1OIq7m-lz-qNBg7LbzWoEeODMvgikSDWZ3SdgpX460EVsWqMUgtIXqbZDdkBgT8WwIhRnvRrsub7Xp9Kos2Wcg", "width": 1000}], "place_id": "ChIJd2m-EDzPCUcRWxmqZ_KJRhM", "plus_code": {"compound_code": "3Q83+VM Dresden, Germany", "global_code": "9F3M3Q83+VM"}, "price_level": 2, "rating": 4.7, "reference": "ChIJd2m-EDzPCUcRWxmqZ_KJRhM", "scope": "GOOGLE", "types": ["bar", "restaurant", "food", "point_of_interest", "establishment"], "user_ratings_total": 1063, "vicinity": "G\u00f6rlitzer Str. 11, Dresden"}, {"business_status": "OPERATIONAL", "geometry": {"location": {"lat": 51.0493388, "lng": 13.7390242}, "viewport": {"northeast": {"lat": 51.05103622989273, "lng": 13.74037837989272}, "southwest": {"lat": 51.04833657010729, "lng": 13.73767872010728}}}, "icon": "https://maps.gstatic.com/mapfiles/place_api/icons/v1/png_71/restaurant-71.png", "icon_background_color": "#FF9E67", "icon_mask_base_uri": "https://maps.gstatic.com/mapfiles/place_api/icons/v2/restaurant_pinlet", "name": "SAUSALITOS", "opening_hours": {"open_now": true}, "photos": [{"height": 1080, "html_attributions": ["<a href=\"https://maps.google.com/maps/contrib/106116983883155603835\">A Google User</a>"], "photo_reference": "AUGGfZmlMeBSke8JLi5u-6FSkA_E1Ie6GaloBibNbgJbvyusqZu198oxOQGsm5AJUZrnkDf-2KiKOeZV0-AiLWVL_SDvT25bFsPSba3r_U0GNyIVq-s_soSiuElE_FAX16XXFOTPWBC_HsTQjPLl2WViWarl9qxy2XKKupT87YOHfAGtVr7F", "width": 1920}], "place_id": "ChIJV9nQ0ozPCUcRnHcl4NsCK08", "plus_code": {"compound_code": "2PXQ+PJ Dresden, Germany", "global_code": "9F3M2PXQ+PJ"}, "price_level": 2, "rating": 3.8, "reference": "ChIJV9nQ0ozPCUcRnHcl4NsCK08", "scope": "GOOGLE", "types": ["restaurant", "bar", "food", "point_of_interest", "establishment"], "user_ratings_total": 1037, "vicinity": "Altmarkt 5-6, Dresden"}, {"business_status": "OPERATIONAL", "geometry": {"location": {"lat": 51.0665473, "lng": 13.7537828}, "viewport": {"northeast": {"lat": 51.06786042989273, "lng": 13.75517782989272}, "southwest": {"lat": 51.06516077010728, "lng": 13.75247817010728}}}, "icon": "https://maps.gstatic.com/mapfiles/place_api/icons/v1/png_71/bar-71.png", "icon_background_color": "#FF9E67", "icon_mask_base_uri": "https://maps.gstatic.com/mapfiles/place_api/icons/v2/bar_pinlet", "name": "Weinbar - vinBistro", "opening_hours": {"open_now": true}, "photos": [{"height": 2336, "html_attributions": ["<a href=\"https://maps.google.com/maps/contrib/106584821095224637871\">A Google User</a>"], "photo_reference": "AUGGfZmLWCWeURNNljYBPTGQNAM6JsE1SVDKzF4nOrOxTO3uPLwDk1yF8C78W96w8v2d1why_vU7wobxYe-zHsl58cIoL8Ak0BWCFCtJRo9qwmY-ESN_iCriF7VCbe-vAz3YLdMkK3poyHoLCFQYnxIz2oV1Zn_8SJ5KPrSYaej_4Y0n-RL-", "width": 3504}], "place_id": "ChIJNfQLHjzPCUcRS7wR-7BpDkI", "plus_code": {"compound_code": "3Q83+JG Dresden, Germany", "global_code": "9F3M3Q83+JG"}, "rating": 4.7, "reference": "ChIJNfQLHjzPCUcRS7wR-7BpDkI", "scope": "GOOGLE", "types": ["bar", "restaurant", "food", "point_of_interest", "establishment"], "user_ratings_total": 40, "vicinity": "G\u00f6rlitzer Str. 1, Dresden"}, {"business_status": "OPERATIONAL", "geometry": {"location": {"lat": 51.0689041, "lng": 13.7553469}, "viewport": {"northeast": {"lat": 51.07026922989272, "lng": 13.75671152989272}, "southwest": {"lat": 51.06756957010727, "lng": 13.75401187010728}}}, "icon": "https://maps.gstatic.com/mapfiles/place_api/icons/v1/png_71/restaurant-71.png", "icon_background_color": "#FF9E67", "icon_mask_base_uri": "https://maps.gstatic.com/mapfiles/place_api/icons/v2/restaurant_pinlet", "name": "El Cubanito", "opening_hours": {"open_now": true}, "photos": [{"height": 2336, "html_attributions": ["<a href=\"https://maps.google.com/maps/contrib/103359718239608701431\">El Cubanito</a>"], "photo_reference": "AUGGfZmyTg8TfiJYcIxVJj6-G_-15bE9U8rJQNHdRtBaNgp0ClXGGkliTWJHaUCElB_qNVzDa5uPPxLVpZaTFS2gskV9sqOrv1z_6DgAoicLe_dn8r5TP8RshvphHH6g5Nc4KKIq1ycn-AGgfYLm9wF8MQ2lgyWWi30r4Pk2lGXAGjR0Dkb3", "width": 3504}], "place_id": "ChIJYceoYjzPCUcRwQqib_Rc-BQ", "plus_code": {"compound_code": "3Q94+H4 Dresden, Germany", "global_code": "9F3M3Q94+H4"}, "price_level": 2, "rating": 4.5, "reference": "ChIJYceoYjzPCUcRwQqib_Rc-BQ", "scope": "GOOGLE", "types": ["bar", "restaurant", "food", "point_of_interest", "establishment"], "user_ratings_total": 641, "vicinity": "Sebnitzer Str. 8B, Dresden"}, {"business_status": "OPERATIONAL", "geometry": {"location": {"lat": 51.0499393, "lng": 13.7368966}, "viewport": {"northeast": {"lat": 51.05147202989271, "lng": 13.73837962989272}, "southwest": {"lat": 51.04877237010727, "lng": 13.73567997010728}}}, "icon": "https://maps.gstatic.com/mapfiles/place_api/icons/v1/png_71/restaurant-71.png", "icon_background_color": "#FF9E67", "icon_mask_base_uri": "https://maps.gstatic.com/mapfiles/place_api/icons/v2/restaurant_pinlet", "name": "HANS IM GL\u00dcCK - DRESDEN Altmarkt", "opening_hours": {"open_now": true}, "photos": [{"height": 2333, "html_attributions": ["<a href=\"https://maps.google.com/maps/contrib/118422025047455031309\">Hans im Gl\u00fcck</a>"], "photo_reference": "AUGGfZlbEafsUHsKJqG6Rj3MGXrTkEAuEOKNp6d5kZKEvkEpo0w_rfgXq4eW15pQaL3jddEv9jGvASmPtvSqxS5tWJ3ckGpHOZgYr-x8xtf0xWQPgO5YHdrMkmG2YPCEQnHr0ohLjsVvig5aZHHYSwKszBL2N9AmaOBmqibNEnU2njYRpx_U", "width": 3500}], "place_id": "ChIJIa4Ip2fPCUcRCsvQ5lN86Io", "plus_code": {"compound_code": "2PXP+XQ Dresden, Germany", "global_code": "9F3M2PXP+XQ"}, "price_level": 2, "rating": 4.5, "reference": "ChIJIa4Ip2fPCUcRCsvQ5lN86Io", "scope": "GOOGLE", "types": ["night_club", "bar", "restaurant", "food", "point_of_interest", "establishment"], "user_ratings_total": 8862, "vicinity": "Altmarkt 24, Dresden"}, {"business_status": "OPERATIONAL", "geometry": {"location": {"lat": 51.0514372, "lng": 13.7371979}, "viewport": {"northeast": {"lat": 51.05283077989272, "lng": 13.73867972989272}, "southwest": {"lat": 51.05013112010727, "lng": 13.73598007010728}}}, "icon": "https://maps.gstatic.com/mapfiles/place_api/icons/v1/png_71/restaurant-71.png", "icon_background_color": "#FF9E67", "icon_mask_base_uri": "https://maps.gstatic.com/mapfiles/place_api/icons/v2/restaurant_pinlet", "name": "ALEX Dresden am Schloss", "opening_hours": {"open_now": true}, "photos": [{"height": 3888, "html_attributions": ["<a href=\"https://maps.google.com/maps/contrib/110481823563899758762\">Markus</a>"], "photo_reference": "AUGGfZm9ikEKNV2_0TF8rB9wWBvbQ_ftf0r_KduskwlU0lGIlf6FVHZEUc2DHxOOVgJFx5U_FOuA0iX4lAKkiGIn45mqsXsDlU_qFc8t3mfNzWy7UJC5fLVF5b91MfBZTWjhYAIPqD9Bw1f7INrS20qjz0PcjF8m4536HAvg-vqgB6PdQkc8", "width": 6192}], "place_id": "ChIJkVi4yGfPCUcRImArECqlgbA", "plus_code": {"compound_code": "3P2P+HV Dresden, Germany", "global_code": "9F3M3P2P+HV"}, "price_level": 2, "rating": 4.2, "reference": "ChIJkVi4yGfPCUcRImArECqlgbA", "scope": "GOOGLE", "types": ["restaurant", "bakery", "bar", "cafe", "food", "point_of_interest", "store", "establishment"], "user_ratings_total": 6719, "vicinity": "Schlo\u00dfstra\u00dfe 7-9, Dresden"}, {"business_status": "OPERATIONAL", "geometry": {"location": {"lat": 51.0684085, "lng": 13.7300507}, "viewport": {"northeast": {"lat": 51.06980087989272, "lng": 13.73135922989272}, "southwest": {"lat": 51.06710122010728, "lng": 13.72865957010728}}}, "icon": "https://maps.gstatic.com/mapfiles/place_api/icons/v1/png_71/bar-71.png", "icon_background_color": "#FF9E67", "icon_mask_base_uri": "https://maps.gstatic.com/mapfiles/place_api/icons/v2/bar_pinlet", "name": "Citybeach Dresden", "opening_hours": {"open_now": true}, "photos": [{"height": 2848, "html_attributions": ["<a href=\"https://maps.google.com/maps/contrib/109684533407384266493\">A Google User</a>"], "photo_reference": "AUGGfZlhsRHhxOwqAaX7ZxKA9euZV5LOhIbnVnToYsDcgEplqZBc_blRAbIpijWjBWFMDFD83m-uF1GifpyxtjKYEZbiqR6opbx8eltRCoAFOSYSjTDMFQcdZgFzOuPqAl5jmRxBb7j1Pw6XIyJMuA2DQ7cw-sgcWwyb31wo4Ztwj8f4cqMo", "width": 4272}], "place_id": "ChIJo849lM3PCUcRZIV4W7boDxM", "plus_code": {"compound_code": "3P9H+CX Dresden, Germany", "global_code": "9F3M3P9H+CX"}, "price_level": 2, "rating": 4.5, "reference": "ChIJo849lM3PCUcRZIV4W7boDxM", "scope": "GOOGLE", "types": ["bar", "restaurant", "food", "point_of_interest", "establishment"], "user_ratings_total": 1916, "vicinity": "Leipziger Str. 31, Dresden"}, {"business_status": "OPERATIONAL", "geometry": {"location": {"lat": 51.0527778, "lng": 13.7413889}, "viewport": {"northeast": {"lat": 51.05393082989272, "lng": 13.74269017989272}, "southwest": {"lat": 51.05123117010728, "lng": 13.73999052010728}}}, "icon": "https://maps.gstatic.com/mapfiles/place_api/icons/v1/png_71/restaurant-71.png", "icon_background_color": "#FF9E67", "icon_mask_base_uri": "https://maps.gstatic.com/mapfiles/place_api/icons/v2/restaurant_pinlet", "name": "Las Tapas", "opening_hours": {"open_now": true}, "photos": [{"height": 3024, "html_attributions": ["<a href=\"https://maps.google.com/maps/contrib/102960399610942134093\">thiagomara leal</a>"], "photo_reference": "AUGGfZmC4MsmalJHLbfZ4-QMBSpU8txyfL7RDOgAQCh--oSvuJsscRNa3VUAK1dMLiXnTFhuizNTcBiVb_Z3w0Zo81tGkbGr63NOMKFp_WBZakeTMtYhnvQP2w4cCVypajVPDl_zzvnaNd28G5bzei76AJj6m-QVFV3SRZ5zNVFioYN7pNsz", "width": 4032}], "place_id": "ChIJD1uiIGfPCUcRA4iMGieN1hI", "plus_code": {"compound_code": "3P3R+4H Dresden, Germany", "global_code": "9F3M3P3R+4H"}, "price_level": 2, "rating": 4.5, "reference": "ChIJD1uiIGfPCUcRA4iMGieN1hI", "scope": "GOOGLE", "types": ["bar", "restaurant", "food", "point_of_interest", "establishment"], "user_ratings_total": 2910, "vicinity": "M\u00fcnzgasse 4, Dresden"}, {"business_status": "OPERATIONAL", "geometry": {"location": {"lat": 51.06803, "lng": 13.75249}, "viewport": {"northeast": {"lat": 51.06931292989272, "lng": 13.75385022989272}, "southwest": {"lat": 51.06661327010728, "lng": 13.75115057010728}}}, "icon": "https://maps.gstatic.com/mapfiles/place_api/icons/v1/png_71/generic_business-71.png", "icon_background_color": "#7B9EB0", "icon_mask_base_uri": "https://maps.gstatic.com/mapfiles/place_api/icons/v2/generic_pinlet", "name": "Carpe Noctem Shisha Bar Dresden", "opening_hours": {"open_now": true}, "photos": [{"height": 1080, "html_attributions": ["<a href=\"https://maps.google.com/maps/contrib/100704809210973169503\">\u0420\u0438\u043d\u0430\u0442 \u041c</a>"], "photo_reference": "AUGGfZnOWMSpPwK_ma7a5aqjLk8Jhtln5n1zirNjNwkb7yphjbpmGRttbDXDU6fr3gAjIGIk5lZpxzBUHp-Fwsru2OTbKAzaxvX6cdvxZcksC41kwNBIRBKYnccGKeAPa5FV07c7GBxvjvDfOx_U5dOTLqkKEj5JgmgynelSt1FKLtaPUF4r", "width": 1620}], "place_id": "ChIJmRc8SjzPCUcR7Xgrkfur3o4", "plus_code": {"compound_code": "3Q92+6X Dresden, Germany", "global_code": "9F3M3Q92+6X"}, "price_level": 2, "rating": 4.6, "reference": "ChIJmRc8SjzPCUcR7Xgrkfur3o4", "scope": "GOOGLE", "types": ["bar", "restaurant", "food", "point_of_interest", "establishment"], "user_ratings_total": 495, "vicinity": "Jordanstra\u00dfe 27, Dresden"}, {"business_status": "OPERATIONAL", "geometry": {"location": {"lat": 51.0510028, "lng": 13.734778}, "viewport": {"northeast": {"lat": 51.05225437989272, "lng": 13.73608642989272}, "southwest": {"lat": 51.04955472010727, "lng": 13.73338677010727}}}, "icon": "https://maps.gstatic.com/mapfiles/place_api/icons/v1/png_71/restaurant-71.png", "icon_background_color": "#FF9E67", "icon_mask_base_uri": "https://maps.gstatic.com/mapfiles/place_api/icons/v2/restaurant_pinlet", "name": "Imbiss Curry24", "opening_hours": {"open_now": true}, "photos": [{"height": 1536, "html_attributions": ["<a href=\"https://maps.google.com/maps/contrib/113339640577362098577\">Ingo Birnbacher</a>"], "photo_reference": "AUGGfZlPjvh8SkBA6HpJNQVXRKVtBhFvbabbKYR7VyU9c1UargkxHn3mhIX1tXJf1sjx4MB_eP2nqnUiBjuyvexLUlE0YG8CtH7hw1dh3pINWU17u52CbPXQR5biOUCKorIBV2J_Ne6kOiZbovSAgcdbfYMtx6v95GfU8PAgTprouKmfHPeq", "width": 2048}], "place_id": "ChIJLfPWQ2bPCUcRvwlsPNwahf0", "plus_code": {"compound_code": "3P2M+CW Dresden, Germany", "global_code": "9F3M3P2M+CW"}, "price_level": 1, "rating": 4.3, "reference": "ChIJLfPWQ2bPCUcRvwlsPNwahf0", "scope": "GOOGLE", "types": ["restaurant", "food", "point_of_interest", "establishment"], "user_ratings_total": 1966, "vicinity": "Wilsdruffer Str. 24, Dresden"}, {"business_status": "OPERATIONAL", "geometry": {"location": {"lat": 51.0483633, "lng": 13.7366829}, "viewport": {"northeast": {"lat": 51.04970822989272, "lng": 13.73812722989272}, "southwest": {"lat": 51.04700857010727, "lng": 13.73542757010728}}}, "icon": "https://maps.gstatic.com/mapfiles/place_api/icons/v1/png_71/restaurant-71.png", "icon_background_color": "#FF9E67", "icon_mask_base_uri": "https://maps.gstatic.com/mapfiles/place_api/icons/v2/restaurant_pinlet", "name": "Aposto Dresden", "opening_hours": {"open_now": true}, "photos": [{"height": 2988, "html_attributions": ["<a href=\"https://maps.google.com/maps/contrib/103996621062381526005\">Patrick Maul</a>"], "photo_reference": "AUGGfZkJHuURN5ejoa_vWtY537nK0LlRr3g4SMYHntmg1rj8p2UPzMfSs5RESFRdamDnksfBmhr_jjpqJMQgcGoc8gFTNd67YNRr4-aBKHycgUqVXoul6S_TzxcBkX9yzbmjE4a1A3IuwRqnNjL7r8p-y6SWIKWcwrrL5KDW25JL0rymPoSm", "width": 5312}], "place_id": "ChIJiRc3P2fPCUcRLLTZE5Aq8yI", "plus_code": {"compound_code": "2PXP+8M Dresden, Germany", "global_code": "9F3M2PXP+8M"}, "price_level": 2, "rating": 4.3, "reference": "ChIJiRc3P2fPCUcRLLTZE5Aq8yI", "scope": "GOOGLE", "types": ["restaurant", "food", "point_of_interest", "establishment"], "user_ratings_total": 2880, "vicinity": "Seestra\u00dfe 10, Dresden"}, {"business_status": "OPERATIONAL", "geometry": {"location": {"lat": 51.0702982, "lng": 13.7473097}, "viewport": {"northeast": {"lat": 51.07165747989272, "lng": 13.74864462989272}, "southwest": {"lat": 51.06895782010728, "lng": 13.74594497010728}}}, "icon": "https://maps.gstatic.com/mapfiles/place_api/icons/v1/png_71/restaurant-71.png", "icon_background_color": "#FF9E67", "icon_mask_base_uri": "https://maps.gstatic.com/mapfiles/place_api/icons/v2/restaurant_pinlet", "name": "Hellmuts", "opening_hours": {"open_now": false}, "photos": [{"height": 5472, "html_attributions": ["<a href=\"https://maps.google.com/maps/contrib/115011443470494431903\">Bernd Fritsche</a>"], "photo_reference": "AUGGfZlY8P2k6SnLUSD9ueJDHxrhHS1mrUQvgjwAPQaUkcti0ypLyuG-Juvr_XAzhHYryXK8tMxSkbGie7LYqAVtkJwnzIWEzTnY-uaaEKgXYrG0_wUWyErWJUkn0-sWEtG4zbu0lHkv00HabSAAHJApxGdCfrpsS00jmgXPyV-dIJvEaxkS", "width": 7296}], "place_id": "ChIJAY-athfPCUcRgqa4PXYAa74", "plus_code": {"compound_code": "3PCW+4W Dresden, Germany", "global_code": "9F3M3PCW+4W"}, "price_level": 2, "rating": 4.6, "reference": "ChIJAY-athfPCUcRgqa4PXYAa74", "scope": "GOOGLE", "types": ["bar", "restaurant", "food", "point_of_interest", "establishment"], "user_ratings_total": 630, "vicinity": "Eschenstra\u00dfe 11, Dresden"}, {"business_status": "OPERATIONAL", "geometry": {"location": {"lat": 51.0425203, "lng": 13.7522664}, "viewport": {"northeast": {"lat": 51.04399392989273, "lng": 13.75330762989272}, "southwest": {"lat": 51.04129427010729, "lng": 13.75060797010728}}}, "icon": "https://maps.gstatic.com/mapfiles/place_api/icons/v1/png_71/restaurant-71.png", "icon_background_color": "#FF9E67", "icon_mask_base_uri": "https://maps.gstatic.com/mapfiles/place_api/icons/v2/restaurant_pinlet", "name": "Restaurant & Veranstaltungsst\u00e4tte - Wachstube in Dresden", "opening_hours": {"open_now": false}, "photos": [{"height": 2250, "html_attributions": ["<a href=\"https://maps.google.com/maps/contrib/115947491242500043751\">Thomas Marr</a>"], "photo_reference": "AUGGfZnn67_dOkfq1WI3Ka0H2bt7dpyVykQN5Ug6SzO0zmYKrqwNcJLc9YMpMpITncI-ZNcAQcPDaMsbvF0DJaXMiKs0_RRZyUfZSC7YoomoECckqmrQXWXzkHiwZFlB9VIlW2ibd_vOiO5ICkzb1hFD7fI6ZQUxl-IWkbLlk6zWdZQlYnzs", "width": 4000}], "place_id": "ChIJ3zE9kVfPCUcR48_FQ9oDWlg", "plus_code": {"compound_code": "2QV2+2W Dresden, Germany", "global_code": "9F3M2QV2+2W"}, "price_level": 2, "rating": 4.2, "reference": "ChIJ3zE9kVfPCUcR48_FQ9oDWlg", "scope": "GOOGLE", "types": ["restaurant", "bar", "food", "point_of_interest", "establishment"], "user_ratings_total": 1788, "vicinity": "Lenn\u00e9stra\u00dfe 9, Dresden"}]