[{"business_status": "OPERATIONAL", "geometry": {"location": {"lat": 45.0669785, "lng": 7.6922656}, "viewport": {"northeast": {"lat": 45.06833437989273, "lng": 7.693622879892722}, "southwest": {"lat": 45.06563472010728, "lng": 7.690923220107278}}}, "icon": "https://maps.gstatic.com/mapfiles/place_api/icons/v1/png_71/bar-71.png", "icon_background_color": "#FF9E67", "icon_mask_base_uri": "https://maps.gstatic.com/mapfiles/place_api/icons/v2/bar_pinlet", "name": "Royal Princess Pub", "opening_hours": {"open_now": true}, "photos": [{"height": 3456, "html_attributions": ["<a href=\"https://maps.google.com/maps/contrib/111309305845272944035\">Danilo Marino</a>"], "photo_reference": "AUGGfZniKZyNTCCCf-wGtElzLtvqLVKKn__Uppm7qWOu7yNfcVUFxPeGCr5y8Cu-rzbsXfqyt3FIlNOoT1dIsIohIawQfpBDfmxeCF8Kuw0C6Df3OEegyP7HlI4cCSSpeC3nu_zg6IiLmqbmChcUrvi_oeO0RXqZZ8wQnp9CC2QrazJ2TloU", "width": 4608}], "place_id": "ChIJ_x18YmNtiEcRpAS1hZcXP3A", "plus_code": {"compound_code": "3M8R+RW Turin, Metropolitan City of Turin, Italy", "global_code": "8FQ93M8R+RW"}, "price_level": 2, "rating": 3.6, "reference": "ChIJ_x18YmNtiEcRpAS1hZcXP3A", "scope": "GOOGLE", "types": ["bar", "point_of_interest", "establishment"], "user_ratings_total": 468, "vicinity": "Via Po, 43, Torino"}, {"business_status": "OPERATIONAL", "geometry": {"location": {"lat": 45.0698391, "lng": 7.7026456}, "viewport": {"northeast": {"lat": 45.07116262989272, "lng": 7.704076079892722}, "southwest": {"lat": 45.06846297010728, "lng": 7.701376420107279}}}, "icon": "https://maps.gstatic.com/mapfiles/place_api/icons/v1/png_71/bar-71.png", "icon_background_color": "#FF9E67", "icon_mask_base_uri": "https://maps.gstatic.com/mapfiles/place_api/icons/v2/bar_pinlet", "name": "Pub Net.Uno - Pub a Torino", "opening_hours": {"open_now": true}, "photos": [{"height": 6120, "html_attributions": ["<a href=\"https://maps.google.com/maps/contrib/101916322898754503597\">Renato Perrotta</a>"], "photo_reference": "AUGGfZld-07RGjdT5uUU72B0I7G5BMSjw9aTsV7S2CWraUO3ISchjWprFazZfZq1AGITh2WoySyx3WP4tJuoWuH8mQRwjooirEmTLE7cgz-FDLb6Yio_1ok-niYK-SqcwHDIa9rdqBzQucA3-11pITsXARMuUKcctGd5z7EHqCT_FajniZ4Q", "width": 8160}], "place_id": "ChIJtYMMc4NyiEcRxZFycZzMM3s", "plus_code": {"compound_code": "3P93+W3 Turin, Metropolitan City of Turin, Italy", "global_code": "8FQ93P93+W3"}, "rating": 4.4, "reference": "ChIJtYMMc4NyiEcRxZFycZzMM3s", "scope": "GOOGLE", "types": ["bar", "point_of_interest", "establishment"], "user_ratings_total": 153, "vicinity": "Via Eusebio Bava, 45/D F, Torino"}, {"business_status": "OPERATIONAL", "geometry": {"location": {"lat": 45.0586488, "lng": 7.680527099999999}, "viewport": {"northeast": {"lat": 45.05997502989272, "lng": 7.681956579892722}, "southwest": {"lat": 45.05727537010728, "lng": 7.679256920107278}}}, "icon": "https://maps.gstatic.com/mapfiles/place_api/icons/v1/png_71/bar-71.png", "icon_background_color": "#FF9E67", "icon_mask_base_uri": "https://maps.gstatic.com/mapfiles/place_api/icons/v2/bar_pinlet", "name": "Toccalmatto Torino", "opening_hours": {"open_now": true}, "photos": [{"height": 3000, "html_attributions": ["<a href=\"https://maps.google.com/maps/contrib/112659543190240877752\">unaynohay</a>"], "photo_reference": "AUGGfZmrszXeEvOPnn6l8FMblTXpe5i2nLKc5ZxDLAgEQZ7LkYD47jxWSqnxxcPuAnv24sCQWwXPdsHDwDFVKfegLuu42w3LQPgJ-5JymyE0qcJ8Tx94ZIiReDMYxN9PbbmZE9S95eabxJZ6FB7b6ryuaBZP06JqIA47tSw5KPlw92_IViRw", "width": 4000}], "place_id": "ChIJX06gKhttiEcRAR-uMuxDqXU", "plus_code": {"compound_code": "3M5J+F6 Turin, Metropolitan City of Turin, Italy", "global_code": "8FQ93M5J+F6"}, "rating": 4.8, "reference": "ChIJX06gKhttiEcRAR-uMuxDqXU", "scope": "GOOGLE", "types": ["liquor_store", "bar", "restaurant", "point_of_interest", "food", "store", "establishment"], "user_ratings_total": 301, "vicinity": "Via Silvio Pellico, 1A, Torino"}, {"business_status": "OPERATIONAL", "geometry": {"location": {"lat": 45.0773879, "lng": 7.667193399999999}, "viewport": {"northeast": {"lat": 45.07878647989272, "lng": 7.668532179892721}, "southwest": {"lat": 45.07608682010728, "lng": 7.665832520107277}}}, "icon": "https://maps.gstatic.com/mapfiles/place_api/icons/v1/png_71/bar-71.png", "icon_background_color": "#FF9E67", "icon_mask_base_uri": "https://maps.gstatic.com/mapfiles/place_api/icons/v2/bar_pinlet", "name": "New Castle", "opening_hours": {"open_now": true}, "photos": [{"height": 2250, "html_attributions": ["<a href=\"https://maps.google.com/maps/contrib/109663736391506418249\">A Google User</a>"], "photo_reference": "AUGGfZm6qI9ol03RkPMkux-Cb9S-40V3tgE5MSBwaieI44WFpHa_9LaVY84esKujeIgFPqddIiLmhOLihTmO37t35mktdIQf55boonPKN0G3SanpplG47Ea57iG0FSyBy6zlDcchmkByNowMy7JI4gDbqlUyd7ikt6j07w0grwQZ2O9Sr0OK", "width": 4000}], "place_id": "ChIJGVzsfQhtiEcRw35hKJaUR0M", "plus_code": {"compound_code": "3MG8+XV Turin, Metropolitan City of Turin, Italy", "global_code": "8FQ93MG8+XV"}, "price_level": 2, "rating": 4.2, "reference": "ChIJGVzsfQhtiEcRw35hKJaUR0M", "scope": "GOOGLE", "types": ["bar", "point_of_interest", "establishment"], "user_ratings_total": 1152, "vicinity": "L.go Luigi Cibrario, 9, Torino"}, {"business_status": "OPERATIONAL", "geometry": {"location": {"lat": 45.0760858, "lng": 7.669365699999999}, "viewport": {"northeast": {"lat": 45.07749792989272, "lng": 7.670555529892724}, "southwest": {"lat": 45.07479827010727, "lng": 7.66785587010728}}}, "icon": "https://maps.gstatic.com/mapfiles/place_api/icons/v1/png_71/restaurant-71.png", "icon_background_color": "#FF9E67", "icon_mask_base_uri": "https://maps.gstatic.com/mapfiles/place_api/icons/v2/restaurant_pinlet", "name": "St. Martin pub", "opening_hours": {"open_now": true}, "photos": [{"height": 366, "html_attributions": ["<a href=\"https://maps.google.com/maps/contrib/110456462541746763038\">Simone Vacca</a>"], "photo_reference": "AUGGfZmDIBCRxUKxr1bcerhIsnhf1gAfP0I-I25a0hURLHD48Y6eA7j5heLfoVhTXDSmWwhPRWaeyAG_0OFVOHRvOp1PoBdlIxGZzCNDwkEHOH6MpwtfkBYJdys7s2a3YGgWspe--T6fQ9x2d07nV0PCEBxsrwq2y1kukcgcX8reV-51KLRl", "width": 550}], "place_id": "ChIJJ09p2AhtiEcRR4reXzjGaPg", "plus_code": {"compound_code": "3MG9+CP Turin, Metropolitan City of Turin, Italy", "global_code": "8FQ93MG9+CP"}, "price_level": 2, "rating": 4.3, "reference": "ChIJJ09p2AhtiEcRR4reXzjGaPg", "scope": "GOOGLE", "types": ["restaurant", "cafe", "bar", "point_of_interest", "food", "establishment"], "user_ratings_total": 2587, "vicinity": "Corso S. Martino, 0/b, Torino"}, {"business_status": "OPERATIONAL", "geometry": {"location": {"lat": 45.0617027, "lng": 7.6812079}, "viewport": {"northeast": {"lat": 45.06302802989273, "lng": 7.68262967989272}, "southwest": {"lat": 45.06032837010729, "lng": 7.679930020107276}}}, "icon": "https://maps.gstatic.com/mapfiles/place_api/icons/v1/png_71/restaurant-71.png", "icon_background_color": "#FF9E67", "icon_mask_base_uri": "https://maps.gstatic.com/mapfiles/place_api/icons/v2/restaurant_pinlet", "name": "Huntsman Pub", "opening_hours": {"open_now": true}, "photos": [{"height": 3024, "html_attributions": ["<a href=\"https://maps.google.com/maps/contrib/114865450416288702876\">PIERO VERGANTE</a>"], "photo_reference": "AUGGfZl0qeVyFt5e1n3J_RvmiFCeAzWrV7ailMNekvzLoAt7tIfQEFdhRtO2rGKoKU7AJnKPEsMzwuOtuBhUkh264YjNsANmB8nnyiiiq7P0cZrdcZFDtG7QI3PAn9TNM7OG-KgAMSZV-23d6JzmsKYSK48v4KVqOcuwGN3Ng0DcVpSsmL2A", "width": 4032}], "place_id": "ChIJr7RbKxVtiEcRkdz63BjlFBs", "plus_code": {"compound_code": "3M6J+MF Turin, Metropolitan City of Turin, Italy", "global_code": "8FQ93M6J+MF"}, "price_level": 2, "rating": 3.9, "reference": "ChIJr7RbKxVtiEcRkdz63BjlFBs", "scope": "GOOGLE", "types": ["restaurant", "bar", "point_of_interest", "food", "establishment"], "user_ratings_total": 2832, "vicinity": "C.so Vittorio Emanuele II, 43, Torino"}, {"business_status": "OPERATIONAL", "geometry": {"location": {"lat": 45.06452849999999, "lng": 7.687019799999999}, "viewport": {"northeast": {"lat": 45.06581182989272, "lng": 7.687914529892721}, "southwest": {"lat": 45.06311217010727, "lng": 7.685214870107277}}}, "icon": "https://maps.gstatic.com/mapfiles/place_api/icons/v1/png_71/bar-71.png", "icon_background_color": "#FF9E67", "icon_mask_base_uri": "https://maps.gstatic.com/mapfiles/place_api/icons/v2/bar_pinlet", "name": "Open Baladin Torino", "opening_hours": {"open_now": true}, "photos": [{"height": 720, "html_attributions": ["<a href=\"https://maps.google.com/maps/contrib/111055469598976224310\">Open Baladin Torino</a>"], "photo_reference": "AUGGfZkYTJu8LgaxwiaTSUW9EgzfuNWVbogKTINJfBzL1tosaS85JiDVjPpNrDJO333mJ73lGLKbhGi4QvH9Ur4Zmzkb7PsBovw6cGF-LzNXgYbSFvLg-UW0-RIvr9qPasso0bolsLAOIo2ruvbuC29hqS1ntAF64T_O-er8dQtknufhhwl3", "width": 960}], "place_id": "ChIJ7Rio4GVtiEcRThSstoW76-c", "plus_code": {"compound_code": "3M7P+RR Turin, Metropolitan City of Turin, Italy", "global_code": "8FQ93M7P+RR"}, "price_level": 2, "rating": 4.4, "reference": "ChIJ7Rio4GVtiEcRThSstoW76-c", "scope": "GOOGLE", "types": ["bar", "restaurant", "point_of_interest", "food", "establishment"], "user_ratings_total": 5147, "vicinity": "Piazzale Valdo Fusi, 1, Torino"}, {"business_status": "OPERATIONAL", "geometry": {"location": {"lat": 45.0781588, "lng": 7.693145899999999}, "viewport": {"northeast": {"lat": 45.07951207989272, "lng": 7.694502279892722}, "southwest": {"lat": 45.07681242010727, "lng": 7.691802620107278}}}, "icon": "https://maps.gstatic.com/mapfiles/place_api/icons/v1/png_71/bar-71.png", "icon_background_color": "#FF9E67", "icon_mask_base_uri": "https://maps.gstatic.com/mapfiles/place_api/icons/v2/bar_pinlet", "name": "Birrificio Torino", "opening_hours": {"open_now": true}, "photos": [{"height": 4128, "html_attributions": ["<a href=\"https://maps.google.com/maps/contrib/104980162958871751512\">Alessio Castello</a>"], "photo_reference": "AUGGfZm3HKr_MGaaqkFoeqSeWcAX9tkGZiPFuqrzo0_SR-aCNgVRHexul0TmmlJDiZqTnG8eWspw00KXQUvi3cDexhDCFF3AoQ0qV-wkSpF6aRnWPasPbx4gRQTorQ47fc1beOd0O__YFF1HRHMXeLzkECdGdZRaV7Wpix7qfto1K_yXmoBy", "width": 5504}], "place_id": "ChIJRaA6d4JtiEcRcTLL7ubR3Ps", "plus_code": {"compound_code": "3MHV+76 Turin, Metropolitan City of Turin, Italy", "global_code": "8FQ93MHV+76"}, "price_level": 2, "rating": 4.3, "reference": "ChIJRaA6d4JtiEcRcTLL7ubR3Ps", "scope": "GOOGLE", "types": ["bar", "point_of_interest", "establishment"], "user_ratings_total": 3742, "vicinity": "Via Parma, 30, Torino"}, {"business_status": "OPERATIONAL", "geometry": {"location": {"lat": 45.08073539999999, "lng": 7.6723037}, "viewport": {"northeast": {"lat": 45.08205957989272, "lng": 7.673636729892723}, "southwest": {"lat": 45.07935992010728, "lng": 7.670937070107279}}}, "icon": "https://maps.gstatic.com/mapfiles/place_api/icons/v1/png_71/bar-71.png", "icon_background_color": "#FF9E67", "icon_mask_base_uri": "https://maps.gstatic.com/mapfiles/place_api/icons/v2/bar_pinlet", "name": "James Joyce Pub - Torino", "opening_hours": {"open_now": true}, "photos": [{"height": 2268, "html_attributions": ["<a href=\"https://maps.google.com/maps/contrib/116506401282498217480\">A Google User</a>"], "photo_reference": "AUGGfZnPdXRv-8CK9J3gv31LxrKKO8G5EQdLfxwvZdL_p-9LJSXwU0Mia2pLhcgiKr3IzecHoXZrlRuRUEfM_DVaKZRqsZBnZhGyXE7M9kSQJpkBQ91CLUQEuW_HMGaC7vNixeqjMbj2LjMbjwdkBJXukBh9FC0OUz6Svk-WoZDiOs90TT7A", "width": 4032}], "place_id": "ChIJ9XjaPqdtiEcRpR3X90AowWo", "plus_code": {"compound_code": "3MJC+8W Turin, Metropolitan City of Turin, Italy", "global_code": "8FQ93MJC+8W"}, "price_level": 1, "rating": 4.3, "reference": "ChIJ9XjaPqdtiEcRpR3X90AowWo", "scope": "GOOGLE", "types": ["bar", "restaurant", "point_of_interest", "food", "establishment"], "user_ratings_total": 616, "vicinity": "Corso Regina Margherita, 192, Torino"}, {"business_status": "OPERATIONAL", "geometry": {"location": {"lat": 45.0604375, "lng": 7.6859968}, "viewport": {"northeast": {"lat": 45.06177217989272, "lng": 7.687332679892723}, "southwest": {"lat": 45.05907252010727, "lng": 7.684633020107279}}}, "icon": "https://maps.gstatic.com/mapfiles/place_api/icons/v1/png_71/bar-71.png", "icon_background_color": "#FF9E67", "icon_mask_base_uri": "https://maps.gstatic.com/mapfiles/place_api/icons/v2/bar_pinlet", "name": "Six Nations Murphy's Pub", "opening_hours": {"open_now": true}, "photos": [{"height": 4176, "html_attributions": ["<a href=\"https://maps.google.com/maps/contrib/100315965105391509788\">Sabina Olivotto</a>"], "photo_reference": "AUGGfZl27598sE7UnkVYhG90rP5pdo67Ra5dOmj0Q3eALdvaF2Ar11ADW9UH7M9neQfbgywujarDl8JM_d2sg-ov54FJsxHqUZJO7YoM9qKkVVqoQU-FFecmSfaCv7a7-By-BW-BrwRzzJ8O6sETjk-JLmtTUKXeGJSYP-tr60aQ9QFPAa8z", "width": 2366}], "place_id": "ChIJ75szk2dtiEcREtbP6RCfADM", "plus_code": {"compound_code": "3M6P+5C Turin, Metropolitan City of Turin, Italy", "global_code": "8FQ93M6P+5C"}, "price_level": 2, "rating": 4.3, "reference": "ChIJ75szk2dtiEcREtbP6RCfADM", "scope": "GOOGLE", "types": ["bar", "restaurant", "point_of_interest", "food", "establishment"], "user_ratings_total": 2650, "vicinity": "C.so Vittorio Emanuele II, 28, Torino"}, {"business_status": "OPERATIONAL", "geometry": {"location": {"lat": 45.0515722, "lng": 7.6752099}, "viewport": {"northeast": {"lat": 45.05289292989271, "lng": 7.676499779892723}, "southwest": {"lat": 45.05019327010727, "lng": 7.673800120107279}}}, "icon": "https://maps.gstatic.com/mapfiles/place_api/icons/v1/png_71/bar-71.png", "icon_background_color": "#FF9E67", "icon_mask_base_uri": "https://maps.gstatic.com/mapfiles/place_api/icons/v2/bar_pinlet", "name": "Waxy O'Connor Pub", "opening_hours": {"open_now": true}, "photos": [{"height": 4032, "html_attributions": ["<a href=\"https://maps.google.com/maps/contrib/100204681696812051070\">VINCENZO ROSA</a>"], "photo_reference": "AUGGfZnjmYX05LXvZb499civfEcKB-VlTy0slVUkyMaNlHm7MoJWnUPKwWTz2KgdwSbJpTdcWiuaYwBPU-qmr7_Dpdk8QPSqN3uE2rPqXFHihzWUVRwaQffNVKTtV4p2-yH2fOWceLHGqeO4wSOZP-8212C0gF3PAqtD7fio3tGDrHJdXo__", "width": 3024}], "place_id": "ChIJB2mcIkZtiEcRC4NeqByTZLo", "plus_code": {"compound_code": "3M2G+J3 Turin, Metropolitan City of Turin, Italy", "global_code": "8FQ93M2G+J3"}, "price_level": 2, "rating": 4.2, "reference": "ChIJB2mcIkZtiEcRC4NeqByTZLo", "scope": "GOOGLE", "types": ["bar", "restaurant", "point_of_interest", "food", "establishment"], "user_ratings_total": 729, "vicinity": "Piazza Nizza, 77a, Torino"}, {"business_status": "OPERATIONAL", "geometry": {"location": {"lat": 45.054776, "lng": 7.6718534}, "viewport": {"northeast": {"lat": 45.05614792989272, "lng": 7.673359229892721}, "southwest": {"lat": 45.05344827010728, "lng": 7.670659570107278}}}, "icon": "https://maps.gstatic.com/mapfiles/place_api/icons/v1/png_71/bar-71.png", "icon_background_color": "#FF9E67", "icon_mask_base_uri": "https://maps.gstatic.com/mapfiles/place_api/icons/v2/bar_pinlet", "name": "The Overbridge Pub", "opening_hours": {"open_now": true}, "photos": [{"height": 4032, "html_attributions": ["<a href=\"https://maps.google.com/maps/contrib/100578463364731137974\">Marco Domizio</a>"], "photo_reference": "AUGGfZmfawzL0Ip-6rQLGMdocetya2lvgh3nqJrg6YrOxLuAU4iYvWMw7ctJ9DH2GYr81N2Ne943tk0koHjf6SmT45jHmfdzpOO7wIZkf1ILcj2dQPBh2VS3icBUVO2CCuMSNGDzMy0BbolPeyGY7QZIDcNiZIonEKaLmBTOt8tyxqDE0BTG", "width": 2268}], "place_id": "ChIJcwol1IFtiEcRSeKKAziRI_Y", "plus_code": {"compound_code": "3M3C+WP Turin, Metropolitan City of Turin, Italy", "global_code": "8FQ93M3C+WP"}, "price_level": 2, "rating": 4.5, "reference": "ChIJcwol1IFtiEcRSeKKAziRI_Y", "scope": "GOOGLE", "types": ["bar", "restaurant", "point_of_interest", "food", "establishment"], "user_ratings_total": 604, "vicinity": "Corso Germano Sommeiller, 17/c, Torino"}, {"business_status": "OPERATIONAL", "geometry": {"location": {"lat": 45.0762945, "lng": 7.667715400000001}, "viewport": {"northeast": {"lat": 45.07767242989272, "lng": 7.669007379892722}, "southwest": {"lat": 45.07497277010728, "lng": 7.666307720107278}}}, "icon": "https://maps.gstatic.com/mapfiles/place_api/icons/v1/png_71/bar-71.png", "icon_background_color": "#FF9E67", "icon_mask_base_uri": "https://maps.gstatic.com/mapfiles/place_api/icons/v2/bar_pinlet", "name": "Downpatrick", "opening_hours": {"open_now": true}, "photos": [{"height": 3024, "html_attributions": ["<a href=\"https://maps.google.com/maps/contrib/110633025053833247490\">A Google User</a>"], "photo_reference": "AUGGfZkfOm815ROYGrln1IREMdjreBI4xNgJunDYRlqQa16F9UdxdY70Y-8pON9GgxzRrMVq_GZ3ngwdTznmCUAtoyLPSwnrwNdNjwtoKLyyUOo8g3mo56rhzf0_jiPjEVzO2ZL_3BRRIwIT3l1Xpanr1gJwdGmvauZjm_9Fv6WnA1zr0tuZ", "width": 4032}], "place_id": "ChIJwZeIlghtiEcRc04k95l1aIo", "plus_code": {"compound_code": "3MG9+G3 Turin, Metropolitan City of Turin, Italy", "global_code": "8FQ93MG9+G3"}, "price_level": 2, "rating": 4.3, "reference": "ChIJwZeIlghtiEcRc04k95l1aIo", "scope": "GOOGLE", "types": ["bar", "point_of_interest", "establishment"], "user_ratings_total": 468, "vicinity": "C.so Francia, 1, Torino"}, {"business_status": "OPERATIONAL", "geometry": {"location": {"lat": 45.07296119999999, "lng": 7.6654967}, "viewport": {"northeast": {"lat": 45.07425572989273, "lng": 7.666884779892722}, "southwest": {"lat": 45.07155607010728, "lng": 7.664185120107279}}}, "icon": "https://maps.gstatic.com/mapfiles/place_api/icons/v1/png_71/bar-71.png", "icon_background_color": "#FF9E67", "icon_mask_base_uri": "https://maps.gstatic.com/mapfiles/place_api/icons/v2/bar_pinlet", "name": "The Isle Of Skye - Pub", "opening_hours": {"open_now": true}, "photos": [{"height": 3966, "html_attributions": ["<a href=\"https://maps.google.com/maps/contrib/100670082958906885248\">Birreria &quot;The isle of Skye&quot;</a>"], "photo_reference": "AUGGfZl34F5muMdku5iBIuvlXaZsHyC1hnt4PLgM8GEOUPbjo9CLuCbL8QXHMfZTeGlItYPiHxU9cpQtarjt0wS3z30KU9cXRI2jktbVKx5pDCenKinvE_XWN6RdL6r9Qt4VVTsc6Si-OwtFjrQbuazQxa5Rs-LAWpU655RV7zqdAzWSfFcx", "width": 5949}], "place_id": "ChIJpf-5gQVtiEcRYwtIF9cf0dk", "plus_code": {"compound_code": "3MF8+56 Turin, Metropolitan City of Turin, Italy", "global_code": "8FQ93MF8+56"}, "price_level": 2, "rating": 4.2, "reference": "ChIJpf-5gQVtiEcRYwtIF9cf0dk", "scope": "GOOGLE", "types": ["bar", "point_of_interest", "establishment"], "user_ratings_total": 2270, "vicinity": "C.so Inghilterra, 25bis, Torino"}, {"business_status": "OPERATIONAL", "geometry": {"location": {"lat": 45.0742047, "lng": 7.6758418}, "viewport": {"northeast": {"lat": 45.07556687989272, "lng": 7.677161029892723}, "southwest": {"lat": 45.07286722010728, "lng": 7.674461370107279}}}, "icon": "https://maps.gstatic.com/mapfiles/place_api/icons/v1/png_71/bar-71.png", "icon_background_color": "#FF9E67", "icon_mask_base_uri": "https://maps.gstatic.com/mapfiles/place_api/icons/v2/bar_pinlet", "name": "Macgillycuddy's", "opening_hours": {"open_now": true}, "photos": [{"height": 4344, "html_attributions": ["<a href=\"https://maps.google.com/maps/contrib/113828957991271193880\">Emanuele Scocchera</a>"], "photo_reference": "AUGGfZkCmXZk5VieuXC7Wxu5hYVo5HHXMGrAgI-HN-bHUaVKpZggAWwGV4WSRoRc1Vf-oMsbLEau0G2C1_irHwPh2i27KohVenvyj0bk_MYK07cicU3o5rN517ART7xajICoZrbuaLsEswYbVbwsChqoaYBHcuHeXejt6B79iwpZ-jkv9Yra", "width": 5792}], "place_id": "ChIJny68oQxtiEcR9KtGt7HO14M", "plus_code": {"compound_code": "3MFG+M8 Turin, Metropolitan City of Turin, Italy", "global_code": "8FQ93MFG+M8"}, "price_level": 2, "rating": 4.4, "reference": "ChIJny68oQxtiEcR9KtGt7HO14M", "scope": "GOOGLE", "types": ["bar", "restaurant", "point_of_interest", "food", "establishment"], "user_ratings_total": 1369, "vicinity": "Via Bligny, 0, Torino"}, {"business_status": "OPERATIONAL", "geometry": {"location": {"lat": 45.0904145, "lng": 7.6853488}, "viewport": {"northeast": {"lat": 45.09164477989273, "lng": 7.686588429892722}, "southwest": {"lat": 45.08894512010729, "lng": 7.683888770107278}}}, "icon": "https://maps.gstatic.com/mapfiles/place_api/icons/v1/png_71/bar-71.png", "icon_background_color": "#FF9E67", "icon_mask_base_uri": "https://maps.gstatic.com/mapfiles/place_api/icons/v2/bar_pinlet", "name": "EDIT Torino", "opening_hours": {"open_now": true}, "photos": [{"height": 1836, "html_attributions": ["<a href=\"https://maps.google.com/maps/contrib/115797779982443291480\">Il Birronauta</a>"], "photo_reference": "AUGGfZkJp_kvSKe0I3naC9eSnr7xiNvVL1oOGZT4af_g3KUOnLTKlztKLXrz2D8iqGSWjqsj0aj2UtFBo_-9w69zxGGT7OrxAxqpXaH9tXqsMbaOn0PHJFuHZjj5Op7VZuFGY4h4K094X5J3CB-7tktLSGbEE8SSQ_7lAiz26JdTZczQUIhZ", "width": 3264}], "place_id": "ChIJo6lmqZdtiEcR9THPgERuNOI", "plus_code": {"compound_code": "3MRP+54 Turin, Metropolitan City of Turin, Italy", "global_code": "8FQ93MRP+54"}, "price_level": 2, "rating": 4.1, "reference": "ChIJo6lmqZdtiEcR9THPgERuNOI", "scope": "GOOGLE", "types": ["bar", "point_of_interest", "establishment"], "user_ratings_total": 3930, "vicinity": "Piazza Teresa Noce, 15/A, Torino"}, {"business_status": "OPERATIONAL", "geometry": {"location": {"lat": 45.0609045, "lng": 7.684583699999998}, "viewport": {"northeast": {"lat": 45.06224892989272, "lng": 7.685929929892724}, "southwest": {"lat": 45.05954927010727, "lng": 7.68323027010728}}}, "icon": "https://maps.gstatic.com/mapfiles/place_api/icons/v1/png_71/bar-71.png", "icon_background_color": "#FF9E67", "icon_mask_base_uri": "https://maps.gstatic.com/mapfiles/place_api/icons/v2/bar_pinlet", "name": "The Shamrock Inn", "opening_hours": {"open_now": true}, "photos": [{"height": 1200, "html_attributions": ["<a href=\"https://maps.google.com/maps/contrib/108496027907757808032\">A Google User</a>"], "photo_reference": "AUGGfZmVIAaNzPEQPA3fFoBnnF5h5VXULOT7Oy16W98kIMBchg2qT325s_WaLIY_6gi4tvCgm-1ibuQn_TP_x3jinrQEpGSFP9_zhleMb8SjStyEcrCJg-qd3HVr0zOH5BIUnkn1CAWnQM_XUUkY0xhqLWMPqRx7G6_d1sgrErnRdQG7TZ3G", "width": 1599}], "place_id": "ChIJA7HHdGhtiEcRnpbN1jW0cGM", "plus_code": {"compound_code": "3M6M+9R Turin, Metropolitan City of Turin, Italy", "global_code": "8FQ93M6M+9R"}, "price_level": 2, "rating": 4.3, "reference": "ChIJA7HHdGhtiEcRnpbN1jW0cGM", "scope": "GOOGLE", "types": ["bar", "restaurant", "point_of_interest", "food", "establishment"], "user_ratings_total": 1186, "vicinity": "C.so Vittorio Emanuele II, 34, Torino"}, {"business_status": "OPERATIONAL", "geometry": {"location": {"lat": 45.0762486, "lng": 7.6809048}, "viewport": {"northeast": {"lat": 45.07764837989271, "lng": 7.682289429892722}, "southwest": {"lat": 45.07494872010727, "lng": 7.679589770107278}}}, "icon": "https://maps.gstatic.com/mapfiles/place_api/icons/v1/png_71/bar-71.png", "icon_background_color": "#FF9E67", "icon_mask_base_uri": "https://maps.gstatic.com/mapfiles/place_api/icons/v2/bar_pinlet", "name": "Conserveria Torino", "opening_hours": {"open_now": true}, "photos": [{"height": 3280, "html_attributions": ["<a href=\"https://maps.google.com/maps/contrib/114011791668430201344\">Marcello Picchioni</a>"], "photo_reference": "AUGGfZl4W-qhIM-rhUikC8pPpTUYQWfmC_ENLdGRe4zaJQJJeL5GgjlCXbFdQqaEK4rx02u1lhD5wfihoAQinDjGZe6ZH22LaGCrB9yjeGKGTSnl378YSaoG1WqQvXlXy0AU0ZEsbTni3dm_b17PmUimnGe7zWCmySanQ-F3W5PU72aYUgfk", "width": 4557}], "place_id": "ChIJsUaBU3RtiEcRfagmwDLgnZI", "plus_code": {"compound_code": "3MGJ+F9 Turin, Metropolitan City of Turin, Italy", "global_code": "8FQ93MGJ+F9"}, "rating": 4.2, "reference": "ChIJsUaBU3RtiEcRfagmwDLgnZI", "scope": "GOOGLE", "types": ["bar", "point_of_interest", "establishment"], "user_ratings_total": 171, "vicinity": "Piazza Emanuele Filiberto, 11, Torino"}, {"business_status": "OPERATIONAL", "geometry": {"location": {"lat": 45.0710847, "lng": 7.677494399999999}, "viewport": {"northeast": {"lat": 45.07247402989272, "lng": 7.678820129892721}, "southwest": {"lat": 45.06977437010728, "lng": 7.676120470107277}}}, "icon": "https://maps.gstatic.com/mapfiles/place_api/icons/v1/png_71/bar-71.png", "icon_background_color": "#FF9E67", "icon_mask_base_uri": "https://maps.gstatic.com/mapfiles/place_api/icons/v2/bar_pinlet", "name": "La Santa Wine & Spirits Torino", "opening_hours": {"open_now": true}, "photos": [{"height": 4912, "html_attributions": ["<a href=\"https://maps.google.com/maps/contrib/110326145256447500296\">A Google User</a>"], "photo_reference": "AUGGfZnIO7IyBJFOAC-g-B0q0TKwshWI6Aw1jGxulyWh7ziRkY7i_8V2wkfjj5RIVFotvS_vsnyVRw_nArCUbyz5tCvBlBJQvLEo2no_gVIEBsiEn3amBncIZm4NzhdHhhzXqDwYlWBCZfl6E793Q4C4uzgVyouHEiF9VNVJ7HvHmJ_pHg9o", "width": 7360}], "place_id": "ChIJl9Fg4JZtiEcRLSQ8d0SRoN0", "plus_code": {"compound_code": "3MCG+CX Turin, Metropolitan City of Turin, Italy", "global_code": "8FQ93MCG+CX"}, "price_level": 2, "rating": 4.6, "reference": "ChIJl9Fg4JZtiEcRLSQ8d0SRoN0", "scope": "GOOGLE", "types": ["liquor_store", "cafe", "bar", "restaurant", "point_of_interest", "food", "store", "establishment"], "user_ratings_total": 646, "vicinity": "Via Stampatori, 19/h, Torino"}, {"business_status": "OPERATIONAL", "geometry": {"location": {"lat": 45.0496393, "lng": 7.675718099999999}, "viewport": {"northeast": {"lat": 45.05097397989272, "lng": 7.677061929892723}, "southwest": {"lat": 45.04827432010728, "lng": 7.674362270107279}}}, "icon": "https://maps.gstatic.com/mapfiles/place_api/icons/v1/png_71/bar-71.png", "icon_background_color": "#FF9E67", "icon_mask_base_uri": "https://maps.gstatic.com/mapfiles/place_api/icons/v2/bar_pinlet", "name": "Petrarca", "opening_hours": {"open_now": true}, "photos": [{"height": 9000, "html_attributions": ["<a href=\"https://maps.google.com/maps/contrib/109515806162653261098\">Nunzio Giandolfo</a>"], "photo_reference": "AUGGfZlahbOJPyN9cVaOf7mqDbnmptQuOwjlFXouTFiLp14EpiVPHbGd_5d7i96Yp-hEIAulmxTF1P__7a8XuHwEHQw9fJL85ddY7FDs_MshMxOcC6jWcrS-SA-q5UzUmTS5iR7o2_tLr-AC_1bIp9ScOyUApEALJYb8gpobqdbEa7euJ912", "width": 12000}], "place_id": "ChIJVxkPx0htiEcRo6hDcxDomGk", "plus_code": {"compound_code": "2MXG+V7 Turin, Metropolitan City of Turin, Italy", "global_code": "8FQ92MXG+V7"}, "price_level": 1, "rating": 4.4, "reference": "ChIJVxkPx0htiEcRo6hDcxDomGk", "scope": "GOOGLE", "types": ["bar", "point_of_interest", "establishment"], "user_ratings_total": 610, "vicinity": "Via Francesco Petrarca, 7, Torino"}]